chroma_ingestion/__init__.py
chroma_ingestion/cli.py
chroma_ingestion/config.py
chroma_ingestion/py.typed
chroma_ingestion/clients/__init__.py
chroma_ingestion/clients/chroma.py
chroma_ingestion/ingestion/__init__.py
chroma_ingestion/ingestion/agents.py
chroma_ingestion/ingestion/base.py
chroma_ingestion/retrieval/__init__.py
chroma_ingestion/retrieval/retriever.py
chroma_ingestion-0.2.3.dist-info/METADATA
chroma_ingestion-0.2.3.dist-info/WHEEL
chroma_ingestion-0.2.3.dist-info/entry_points.txt
chroma_ingestion-0.2.3.dist-info/RECORD
