Metadata-Version: 2.4
Name: chroma-ingestion
Version: 0.2.3
Summary: Semantic-aware code ingestion and retrieval for ChromaDB
Project-URL: Homepage, https://github.com/chroma-core/chroma-ingestion
Project-URL: Documentation, https://chroma-ingestion.readthedocs.io
Project-URL: Repository, https://github.com/chroma-core/chroma-ingestion
Project-URL: Bug Tracker, https://github.com/chroma-core/chroma-ingestion/issues
Author: Chroma Contributors
License: MIT
Keywords: chromadb,code-search,rag,semantic-search,vector-database
Classifier: Development Status :: 4 - Beta
Classifier: Environment :: Console
Classifier: Intended Audience :: Developers
Classifier: License :: OSI Approved :: MIT License
Classifier: Operating System :: OS Independent
Classifier: Programming Language :: Python :: 3
Classifier: Programming Language :: Python :: 3.11
Classifier: Programming Language :: Python :: 3.12
Classifier: Topic :: Database
Classifier: Topic :: Scientific/Engineering :: Artificial Intelligence
Classifier: Topic :: Software Development :: Libraries :: Python Modules
Requires-Python: >=3.11
Requires-Dist: chromadb>=1.3.5
Requires-Dist: click>=8.0
Requires-Dist: langchain-text-splitters>=1.0.0
Requires-Dist: python-dotenv>=1.0.0
Requires-Dist: pyyaml>=6.0
Provides-Extra: dev
Requires-Dist: mkdocs-material>=9.5; extra == 'dev'
Requires-Dist: mkdocs>=1.5; extra == 'dev'
Requires-Dist: mypy>=1.8; extra == 'dev'
Requires-Dist: nox>=2024.0; extra == 'dev'
Requires-Dist: pre-commit>=3.6; extra == 'dev'
Requires-Dist: pytest-asyncio>=0.23; extra == 'dev'
Requires-Dist: pytest-cov>=4.0; extra == 'dev'
Requires-Dist: pytest>=8.0; extra == 'dev'
Requires-Dist: ruff>=0.4; extra == 'dev'
